{
  "project_info": {
    "project_number": "623168470227",
    "project_id": "lifeplusdev-fde65",
    "storage_bucket": "lifeplusdev-fde65.appspot.com"
  },
  "client": [
    {
      "client_info": {
        "mobilesdk_app_id": "1:623168470227:android:7b16e00effca732f7f6826",
        "android_client_info": {
          "package_name": "com.welfare.blood.donation.dev"
        }
      },
      "oauth_client": [],
      "api_key": [
        {
          "current_key": "AIzaSyDPQjuXVAKsBBGEVm7i60XIC_6J2eqLV3c"
        }
      ],
      "services": {
        "appinvite_service": {
          "other_platform_oauth_client": []
        }
      }
    }
  ],
  "configuration_version": "1"
}